{
    "/js/app.js": "/js/app.js",
    "/css/app.css": "/css/app.css",
    "/js/booking.js": "/js/booking.js",
    "/js/chat.js": "/js/chat.js",
    "/js/client.js": "/js/client.js",
    "/js/dosage.js": "/js/dosage.js",
    "/js/employee.js": "/js/employee.js",
    "/js/employee_details.js": "/js/employee_details.js",
    "/js/file-manager.js": "/js/file-manager.js",
    "/js/mar_sheet.js": "/js/mar_sheet.js",
    "/js/organization.js": "/js/organization.js",
    "/js/route.js": "/js/route.js",
    "/js/service_user.js": "/js/service_user.js",
    "/js/setting.js": "/js/setting.js",
    "/js/system.js": "/js/system.js"
}
